LICENSE
MANIFEST.in
README.rst
requirements.txt
setup.py
pyver/__init__.py
pyver/main.py
pyver/version.py
pyver.egg-info/PKG-INFO
pyver.egg-info/SOURCES.txt
pyver.egg-info/dependency_links.txt
pyver.egg-info/entry_points.txt
pyver.egg-info/not-zip-safe
pyver.egg-info/pbr.json
pyver.egg-info/top_level.txt