Metadata-Version: 1.1
Name: pyver
Version: 1.0.38
Summary: Git-based versioning for Python tools and modules.
Home-page: https://github.com/clearclaw/pyver
Author: J C Lawrence
Author-email: claw@kanga.nu
License: LGPL v3
Download-URL: https://github.com/clearclaw/pyver/tarball/1.0
Keywords: version semver git
Platform: UNKNOWN
Classifier: Development Status :: 4 - Beta
Classifier: Intended Audience :: Developers
Classifier: License :: OSI Approved :: GNU General Public License v3 or later (GPLv3+)
Classifier: Topic :: Utilities
